MulticoreTSNE/__init__.py
MulticoreTSNE/libtsne_multicore.so
MulticoreTSNE/tests/__init__.py
MulticoreTSNE/tests/test_base.py
MulticoreTSNE_modified-0.1.post2.dist-info/LICENSE.txt
MulticoreTSNE_modified-0.1.post2.dist-info/METADATA
MulticoreTSNE_modified-0.1.post2.dist-info/WHEEL
MulticoreTSNE_modified-0.1.post2.dist-info/top_level.txt
MulticoreTSNE_modified-0.1.post2.dist-info/RECORD
